cspyclient/CohortGroup.py
cspyclient/CohortMember.py
cspyclient/DBService.py
cspyclient/ProgressScore.py
cspyclient/SubmissionGrade.py
cspyclient/__init__.py
cspyclient/assignment.py
cspyclient/assignment_report.py
cspyclient/attendance.py
cspyclient/base.py
cspyclient/check.py
cspyclient/cohort.py
cspyclient/cohort_group.py
cspyclient/cohort_member.py
cspyclient/cohort_report.py
cspyclient/config.py
cspyclient/course.py
cspyclient/db_service.py
cspyclient/lead.py
cspyclient/progress_score.py
cspyclient/security.py
cspyclient/session.py
cspyclient/student.py
cspyclient/submission.py
cspyclient/submission_grade.py
cspyclient/template_notebook.py
cspyclient/templates.py
cspyclient/test.py
cspyclient/user.py
cspyclient/user_report.py
cspyclient/utils.py
cspyclient-1.0.19.dist-info/AUTHORS.rst
cspyclient-1.0.19.dist-info/LICENSE
cspyclient-1.0.19.dist-info/METADATA
cspyclient-1.0.19.dist-info/WHEEL
cspyclient-1.0.19.dist-info/top_level.txt
cspyclient-1.0.19.dist-info/RECORD
