Metadata-Version: 2.1
Name: cspyclient
Version: 1.0.19
Summary: An internal tool to work with CoderSchool Backend API
Home-page: UNKNOWN
Author: Minh Hai Do
Author-email: minhdh@coderschool.vn
License: MIT
Platform: UNKNOWN
Classifier: Development Status :: 5 - Production/Stable
Classifier: Intended Audience :: Education
Classifier: License :: OSI Approved :: MIT License
Classifier: Programming Language :: Python :: 3
Requires-Dist: pandas
Requires-Dist: requests
Requires-Dist: cryptography
Requires-Dist: numpy
